Metadata-Version: 2.1
Name: bs32
Version: 0.0.1
Summary: This Lebrary for Main Lebrary ccode
Author: Mohammed Hamza
Author-email: eibdhhs0@gmail.com
Classifier: Operating System :: OS Independent
Classifier: Natural Language :: Arabic
Classifier: Programming Language :: Python :: 3
Classifier: License :: OSI Approved :: MIT License 
License-File: LICENSE
